RWexptest/File_read.py
RWexptest/Unzip.py
RWexptest/_init_.py
RWexptest/DNN/Sample_DNN_Model.py
RWexptest/DNN/__init__.py
RWexptest/Pseqpa/NCBI_Blast_creat_blast.py
RWexptest/Pseqpa/__init__.py
RWexptest/Pseqpa/fasta_process.py
RWexptest/Pseqpa/other_to_fasta.py
RWexptest/Pseqpa/xml_read.py
RWexptest/RNN/__init__.py
RWexptest/RNN/simple_RNN_model.py
RWexptest-0.0.14.dist-info/LICENSE.txt
RWexptest-0.0.14.dist-info/METADATA
RWexptest-0.0.14.dist-info/WHEEL
RWexptest-0.0.14.dist-info/top_level.txt
RWexptest-0.0.14.dist-info/RECORD
