Metadata-Version: 2.1
Name: RWexptest
Version: 0.0.14
Summary: A small example package
Author-email: RuiwangW <2219312248@qq.com>
Project-URL: Homepage, https://github.com/pypa/sampleproject
Project-URL: Bug Tracker, https://github.com/pypa/sampleproject/issues
Classifier: Programming Language :: Python :: 3
Classifier: License :: OSI Approved :: MIT License
Classifier: Operating System :: OS Independent
Requires-Python: >=3.7
License-File: LICENSE.txt
Requires-Dist: numpy
Requires-Dist: scipy
Requires-Dist: Bio
Requires-Dist: pandas
Requires-Dist: rarfile
